ingredients/__init__.py
ingredients/cli.py
ingredients/ingredients.py
ingredients-0.3.0.dist-info/METADATA
ingredients-0.3.0.dist-info/RECORD
ingredients-0.3.0.dist-info/WHEEL
ingredients-0.3.0.dist-info/entry_points.txt
ingredients-0.3.0.dist-info/top_level.txt
