Metadata-Version: 2.1
Name: ingredients
Version: 0.3.0
Summary: ingredients code for practicing python packaging
Home-page: https://github.com/kyoungrok0517/ingredients
Author: Kyoung-Rok Jang
Author-email: kyoungrok.jang@gmail.com
License: MIT license
Keywords: ingredients
Platform: UNKNOWN
Classifier: Development Status :: 2 - Pre-Alpha
Classifier: Intended Audience :: Developers
Classifier: License :: OSI Approved :: MIT License
Classifier: Natural Language :: English
Classifier: Programming Language :: Python :: 2
Classifier: Programming Language :: Python :: 2.7
Classifier: Programming Language :: Python :: 3
Classifier: Programming Language :: Python :: 3.4
Classifier: Programming Language :: Python :: 3.5
Classifier: Programming Language :: Python :: 3.6
Requires-Dist: Click (>=6.0)
